python_selenium_google_form/__init__.py
python_selenium_google_form/main.py
python_selenium_google_form-0.7.2.dist-info/METADATA
python_selenium_google_form-0.7.2.dist-info/WHEEL
python_selenium_google_form-0.7.2.dist-info/top_level.txt
python_selenium_google_form-0.7.2.dist-info/RECORD
