Metadata-Version: 2.1
Name: python_selenium_google_form
Version: 0.7.2
Summary: Automate Google Forms
Requires-Dist: undetected-chromedriver ==3.5.5
Requires-Dist: selenium ==4.23.1
Requires-Dist: setuptools ==71.1.0
